{
    "datasetID": 69,
    "supportID": "6C4D5C33421F2CD1BB4CAC947EC6D58FE27AAC10",
    "rexaID": "0cedee7ef9325127fb946dcdddf8795644e28335",
    "author": "Jinyan Li and Kotagiri Ramamohanarao and Guozhu Dong",
    "title": "Combining the Strength of Pattern Frequency and Distance for Classification",
    "venue": "PAKDD",
    "year": "2001",
    "window": "containing pure categorical attributes. The accuracy is sometimes better (e.g., on the tic-tac-toe data set), but sometimes worse (e.g., on the <b>splice</b> data set). 4.2 Accuracy Variation among Folds The next set of experimental results are used to demonstrate the accuracy variations among the ten folds. We",
    "mykey": 1040
}