{
    "datasetID": 52,
    "supportID": "93187059BF6EAB8DBAE1762B80ED7071F9A435BF",
    "rexaID": "e2b2b723df700c90e69a31a4403b740c2d2a7b2f",
    "author": "Alexander K. Seewald",
    "title": "Dissertation Towards Understanding Stacking Studies of a General Ensemble Learning Scheme ausgefuhrt zum Zwecke der Erlangung des akademischen Grades eines Doktors der technischen Naturwissenschaften",
    "venue": "",
    "year": "",
    "window": "audiology to hepatitis. 79 Compressed glyph visualization for dataset <b>ionosphere</b> Compressed glyph visualization for dataset iris Compressed glyph visualization for dataset labor Compressed glyph visualization for dataset lymph Compressed glyph visualization for",
    "mykey": 1455
}