{
    "datasetID": 144,
    "supportID": "DDE3924C1BF35AB7FC25A1172F08C3089C0CC5A7",
    "rexaID": "7be023799304644bda7d6afa9f31043a1f31511c",
    "author": "Paul O' Dea and David Griffith and Colm O' Riordan",
    "title": "DEPARTMENT OF INFORMATION TECHNOLOGY",
    "venue": "P. O'Dea (NUI",
    "year": "",
    "window": "network (as described earlier), using back-propagation as a learning algorithm, is used to classify the tuples t 1 : : : t n based on the attributes s 1 : : : s n . 5 Results 5.1 The <b>German Credit</b> Data Set In order to facilitate testing of the developed approach, experiments were conducted using the german credit data set 1 . The german credit data set contains information on 1000 loan applicants.",
    "mykey": 2227
}