{
    "datasetID": 74,
    "supportID": "EC7FEEF4845B232307D7A88A8B760D1D4F5536FB",
    "rexaID": "7ee121b26e79c0a7aa5c80979e275fc3592d0638",
    "author": "Giorgio Valentini",
    "title": "Ensemble methods based on bias--variance analysis Theses Series DISI-TH-2003",
    "venue": "Dipartimento di Informatica e Scienze dell'Informazione ",
    "year": "2003",
    "window": "with 4601 instances and 57 continuous attributes. 4.1.1.6 <b>Musk</b> The dataset (available from UCI) describes a set of 102 molecules of which 39 are judged by human experts to be musks and the remaining 63 molecules are judged to be nonmusks. The 166 features that describe",
    "mykey": 2366
}