{
    "datasetID": 151,
    "supportID": "2874A0E977200B03C9F1A3DADEB68D41C11C8089",
    "rexaID": "df61ac3ab404fccb23262b177e5475d1f4c236de",
    "author": "Hiroshi Shimodaira and Jun Okui and Mitsuru Nakai",
    "title": "Modified Minimum Classification Error Learning and Its Application to Neural Networks",
    "venue": "SSPR/SPR",
    "year": "1998",
    "window": "generalization performance of the original MCE learning, optimization of the network architecture and learning parameters is not very important. Table 1. Performance comparison in two-class problems Data set Cancer House <b>Sonar</b> # classes 2 2 2 # training data 420 265 141 # test data 279 170 67 # attributes 9 15 60 Method # hidden units 12 12 12 Bayes/ML 95.0 98.8 100.0 NN/EBP training 91.9 96.3 95.0",
    "mykey": 330
}